numberconverter/NumberConverter.py
numberconverter/__init__.py
numberconverter/test.py
numberconverter-1.0.0.dist-info/METADATA
numberconverter-1.0.0.dist-info/RECORD
numberconverter-1.0.0.dist-info/WHEEL
numberconverter-1.0.0.dist-info/top_level.txt
