Metadata-Version: 2.1
Name: numberconverter
Version: 1.0.0
Summary: numberconverter is created for converting english number to bangla number or reverse
Home-page: https://github.com/mahfuzcmt/engtobngnum
Author: Mahfuz Ahmed
Author-email: mahfuzcmt@gmail.com
License: UNKNOWN
Platform: UNKNOWN
Classifier: Programming Language :: Python :: 3
Classifier: License :: OSI Approved :: MIT License
Classifier: Operating System :: OS Independent
